pitanga/__init__.py
pitanga/config/__init__.py
pitanga/config/settings.py
pitanga/database/__init__.py
pitanga/database/operations.py
pitanga-0.0.1.dist-info/LICENSE
pitanga-0.0.1.dist-info/METADATA
pitanga-0.0.1.dist-info/WHEEL
pitanga-0.0.1.dist-info/top_level.txt
pitanga-0.0.1.dist-info/RECORD
