Metadata-Version: 2.1
Name: pitanga
Version: 0.0.1
Summary: Tools for Database Operations in Python
Author-email: Joab Leite <leitejoab@gmail.com>
License: MIT License
Project-URL: Homepage, https://github.com/cereja-project/pitanga
Project-URL: Bug Tracker, https://github.com/cereja-project/pitanga/issues/new/choose
Keywords: Database,Postgress
Classifier: Programming Language :: Python :: 3
Classifier: Programming Language :: Python :: 3.6
Classifier: Programming Language :: Python :: 3.7
Classifier: Programming Language :: Python :: 3.8
Classifier: Programming Language :: Python :: 3.9
Classifier: Programming Language :: Python :: 3.10
Classifier: Programming Language :: Python :: 3.11
Classifier: Programming Language :: Python :: 3 :: Only
Classifier: License :: OSI Approved :: MIT License
Classifier: Operating System :: OS Independent
Requires-Python: >=3.6
License-File: LICENSE
Requires-Dist: psycopg2-binary
Requires-Dist: cereja
